config.example.yaml
src/__init__.py
src/cli/__init__.py
src/cli/cli.py
src/cli/commands/__init__.py
src/cli/commands/add.py
src/cli/commands/auth.py
src/cli/commands/config.py
src/cli/commands/init.py
src/cli/commands/status.py
src/cli/commands/sync.py
src/cli/wizard.py
src/config/__init__.py
src/config/config_loader.py
src/config/models.py
src/py.typed
src/spotify/__init__.py
src/spotify/auth.py
src/spotify/client.py
src/spotify/models.py
src/sync/__init__.py
src/sync/diff.py
src/sync/engine.py
src/sync/filters.py
src/utils/__init__.py
src/utils/logger.py
spotisync-0.1.2.dist-info/LICENSE
spotisync-0.1.2.dist-info/METADATA
spotisync-0.1.2.dist-info/WHEEL
spotisync-0.1.2.dist-info/entry_points.txt
spotisync-0.1.2.dist-info/RECORD
