Metadata-Version: 2.3
Name: spotisync
Version: 0.1.2
Summary: SpotiSync - Smart syncing for Spotify playlists
License: MIT
Keywords: spotisync,spotify,playlist-sync,music,automation,cli,liked-songs,playlist-manager
Author: Robin Schulz
Author-email: bulletinmybeard@gmail.com
Requires-Python: >=3.12,<4.0
Classifier: Development Status :: 3 - Alpha
Classifier: Environment :: Console
Classifier: Framework :: Pydantic :: 2
Classifier: Intended Audience :: End Users/Desktop
Classifier: License :: OSI Approved :: MIT License
Classifier: Natural Language :: English
Classifier: Operating System :: OS Independent
Classifier: Programming Language :: Python :: 3
Classifier: Programming Language :: Python :: 3.12
Classifier: Programming Language :: Python :: 3.13
Classifier: Topic :: Multimedia :: Sound/Audio
Classifier: Topic :: Utilities
Classifier: Typing :: Typed
Requires-Dist: APScheduler (>=3.11.1,<4.0.0)
Requires-Dist: PyYAML (>=6.0.3,<7.0.0)
Requires-Dist: chalkbox (>=2.3.5,<3.0.0)
Requires-Dist: click (>=8.3.0,<9.0.0)
Requires-Dist: pydantic (>=2.12.4,<3.0.0)
Requires-Dist: pydantic-settings (>=2.12.0,<3.0.0)
Requires-Dist: spotipy (>=2.24.0,<3.0.0)
Project-URL: Documentation, https://github.com/bulletinmybeard/spotisync#readme
Project-URL: Homepage, https://github.com/bulletinmybeard/spotisync
Project-URL: Repository, https://github.com/bulletinmybeard/spotisync
